setup.py
jsonproxy/__init__.py
jsonproxy/iso8601.py
jsonproxy.egg-info/PKG-INFO
jsonproxy.egg-info/SOURCES.txt
jsonproxy.egg-info/dependency_links.txt
jsonproxy.egg-info/top_level.txt