Metadata-Version: 1.0
Name: jsonproxy
Version: 0.1
Summary: Gateway interface between non-standard types and JSON_ serialization.
Home-page: https://maze.io/
Author: Wijnand Modderman-Lenstra
Author-email: maze@pyth0n.org
License: MIT
Keywords: JSON proxy
Platform: UNKNOWN
